seedrcc/__init__.py
seedrcc/_base.py
seedrcc/_constants.py
seedrcc/_utils.py
seedrcc/async_client.py
seedrcc/client.py
seedrcc/exceptions.py
seedrcc/models.py
seedrcc/token.py
seedrcc-2.0.2.dist-info/METADATA
seedrcc-2.0.2.dist-info/WHEEL
seedrcc-2.0.2.dist-info/licenses/LICENSE
seedrcc-2.0.2.dist-info/RECORD
