Metadata-Version: 2.4
Name: seedrcc
Version: 2.0.2
Summary: A comprehensive Python API wrapper for seedr.cc
Project-URL: Homepage, https://github.com/hemantapkh/seedrcc
Project-URL: Documentation, https://seedrcc.readthedocs.io/en/latest/
Project-URL: Bug Tracker, https://github.com/hemantapkh/seedrcc/issues
Author-email: Hemanta Pokharel <yo@hemantapkh.com>
License: MIT License
License-File: LICENSE
Classifier: Development Status :: 5 - Production/Stable
Classifier: Intended Audience :: Developers
Classifier: License :: OSI Approved :: MIT License
Classifier: Operating System :: OS Independent
Classifier: Programming Language :: Python :: 3.9
Classifier: Programming Language :: Python :: 3.10
Classifier: Programming Language :: Python :: 3.11
Classifier: Programming Language :: Python :: 3.12
Classifier: Programming Language :: Python :: 3.13
Classifier: Topic :: Internet
Classifier: Topic :: Software Development :: Libraries :: Python Modules
Classifier: Topic :: Utilities
Classifier: Typing :: Typed
Requires-Python: >=3.9
Requires-Dist: anyio
Requires-Dist: httpx
